example_package_Niclas/__init__.py
example_package_Niclas/example.py
niclas_test_package_thesis-0.1.0.dist-info/licenses/LICENSE.txt
niclas_test_package_thesis-0.1.0.dist-info/METADATA
niclas_test_package_thesis-0.1.0.dist-info/WHEEL
niclas_test_package_thesis-0.1.0.dist-info/top_level.txt
niclas_test_package_thesis-0.1.0.dist-info/RECORD
