Metadata-Version: 2.4
Name: Niclas_test_package_thesis
Version: 0.1.0
Summary: A short description of your package
Author-email: Niclas Brandt <niclasbrandt97@gmail.com>
Classifier: Programming Language :: Python :: 3
Classifier: License :: OSI Approved :: MIT License
Classifier: Operating System :: OS Independent
Requires-Python: >=3.7
License-File: LICENSE.txt
Requires-Dist: requests>=2.0
Requires-Dist: numpy>=1.20
Dynamic: license-file
